NanoAutoGrad/NanoAutoGrad.py
NanoAutoGrad/__init__.py
NanoAutoGrad/engine.py
NanoAutoGrad/network.py
NanoAutoGrad-0.1.2.dist-info/LICENSE
NanoAutoGrad-0.1.2.dist-info/METADATA
NanoAutoGrad-0.1.2.dist-info/WHEEL
NanoAutoGrad-0.1.2.dist-info/top_level.txt
NanoAutoGrad-0.1.2.dist-info/RECORD
