Metadata-Version: 2.1
Name: NanoAutoGrad
Version: 0.1.2
Summary: A miniature implementation of PyTorch's autograd
Home-page: https://github.com/practice404/NanoAutoGrad
Author: Swayam Singh
Author-email: singhswayam008@gmail.com
Classifier: Programming Language :: Python :: 3
Classifier: License :: OSI Approved :: MIT License
Classifier: Operating System :: OS Independent
Requires-Python: >=3.6
License-File: LICENSE
